Workbook

Sheet Start Here
A1: Lab 3: Build an FP&A Formula Model and Dashboard
A3: Course | B3: Generative AI for Finance and Fintech (TGS-2026065050)
A4: TSC mapping | B4: K1 · A2
A5: Objective | B5: Use native finance formulas, scenarios and charts to build an auditable management dashboard.
A6: Scenario | B6: Northstar's CFO needs a monthly performance dashboard and a transparent base/downside forecast.
A7: Expected output | B7: An editable dashboard with actual, budget, variance, forecast and driver views.
A8: Data notice | B8: All names, accounts, transactions and scores are synthetic. Do not replace them with live personal or customer data.
A9: Acceptance | B9: Dashboard charts remain linked to data; all formula checks pass; total variance equals actual less budget; scenarios use assumption cells rather than hard-coded outputs.

Sheet Actuals
A1: Department | B1: Month | C1: Month No | D1: Revenue | E1: Cost of Sales | F1: Operating Expense
A2: Retail | B2: Jan | C2: 1 | D2: 530761 | E2: -231724 | F2: -155692
A3: Retail | B3: Feb | C3: 2 | D3: 503518 | E3: -207028 | F3: -158542
A4: Retail | B4: Mar | C4: 3 | D4: 589110 | E4: -252748 | F4: -171714
A5: Retail | B5: Apr | C5: 4 | D5: 537914 | E5: -235451 | F5: -172890
A6: Retail | B6: May | C6: 5 | D6: 542347 | E6: -220911 | F6: -177848
A7: Retail | B7: Jun | C7: 6 | D7: 608028 | E7: -259484 | F7: -183141
A8: Retail | B8: Jul | C8: 7 | D8: 644804 | E8: -261720 | F8: -186092
A9: Retail | B9: Aug | C9: 8 | D9: 615036 | E9: -264216 | F9: -208121
A10: Retail | B10: Sep | C10: 9 | D10: 648361 | E10: -272045 | F10: -209695
A11: Retail | B11: Oct | C11: 10 | D11: 750496 | E11: -312044 | F11: -207725
A12: Retail | B12: Nov | C12: 11 | D12: 765301 | E12: -316583 | F12: -215550
A13: Retail | B13: Dec | C13: 12 | D13: 733603 | E13: -302355 | F13: -225510
... A49: Digital | B49: Dec | C49: 12 | D49: 923465 | E49: -384928 | F49: -294180

Sheet Budget
A1: Department | B1: Month | C1: Month No | D1: Revenue | E1: Cost of Sales | F1: Operating Expense
A2: Retail | B2: Jan | C2: 1 | D2: 515000 | E2: -216300 | F2: -150000
A3: Retail | B3: Feb | C3: 2 | D3: 537660 | E3: -225817 | F3: -157000
A4: Retail | B4: Mar | C4: 3 | D4: 560320 | E4: -235334 | F4: -164000
A5: Retail | B5: Apr | C5: 4 | D5: 582980 | E5: -244852 | F5: -171000
A6: Retail | B6: May | C6: 5 | D6: 605640 | E6: -254369 | F6: -178000
A7: Retail | B7: Jun | C7: 6 | D7: 628300 | E7: -263886 | F7: -185000
A8: Retail | B8: Jul | C8: 7 | D8: 650960 | E8: -273403 | F8: -192000
A9: Retail | B9: Aug | C9: 8 | D9: 673620 | E9: -282920 | F9: -199000
A10: Retail | B10: Sep | C10: 9 | D10: 696280 | E10: -292438 | F10: -206000
A11: Retail | B11: Oct | C11: 10 | D11: 718940 | E11: -301955 | F11: -213000
A12: Retail | B12: Nov | C12: 11 | D12: 741600 | E12: -311472 | F12: -220000
A13: Retail | B13: Dec | C13: 12 | D13: 764260 | E13: -320989 | F13: -227000
... A49: Digital | B49: Dec | C49: 12 | D49: 1011460 | E49: -424813 | F49: -281000

Sheet Assumptions
A1: Scenario assumptions
A3: Assumption | B3: Value | C3: Owner
A4: Base revenue growth | B4: 0.06 | C4: FP&A Director
A5: Downside revenue growth | B5: -0.03 | C5: FP&A Director
A6: Base COGS % | B6: 0.41 | C6: FP&A Director
A7: Downside COGS % | B7: 0.45 | C7: FP&A Director
A8: Base opex growth | B8: 0.04 | C8: FP&A Director
A9: Downside opex growth | B9: 0.08 | C9: FP&A Director
A10: Discount rate | B10: 0.1 | C10: FP&A Director

Sheet Analysis
A1: Department | B1: Month | C1: Actual Revenue | D1: Budget Revenue | E1: Revenue Variance | F1: Actual EBITDA | G1: Budget EBITDA | H1: EBITDA Variance | I1: Variance % | J1: Commentary status
A2: Retail | B2: Jan | C2: =SUMIFS(Actuals!$D:$D,Actuals!$A:$A,A2,Actuals!$B:$B,B2) -> 530761 | D2: =SUMIFS(Budget!$D:$D,Budget!$A:$A,A2,Budget!$B:$B,B2) -> 515000 | E2: =C2-D2 -> 15761 | F2: =SUMIFS(Actuals!$D:$D,Actuals!$A:$A,A2,Actuals!$B:$B,B2)+SUMIFS(Actuals!$E:$E,Actuals!$A:$A,A2,Actuals!$B:$B,B2)+SUMIFS(Actuals!$F:$F,Actuals!$A:$A,A2,Actuals!$B:$B,B2) -> 143345 | G2: =SUMIFS(Budget!$D:$D,Budget!$A:$A,A2,Budget!$B:$B,B2)+SUMIFS(Budget!$E:$E,Budget!$A:$A,A2,Budget!$B:$B,B2)+SUMIFS(Budget!$F:$F,Budget!$A:$A,A2,Budget!$B:$B,B2) -> 148700 | H2: =F2-G2 -> -5355 | I2: =IFERROR(E2/D2,0) -> 0.030603883 | J2: =IF(ABS(I2)>=5%,"Review","Within threshold") -> Within threshold
A3: Retail | B3: Feb | C3: =SUMIFS(Actuals!$D:$D,Actuals!$A:$A,A3,Actuals!$B:$B,B3) -> 503518 | D3: =SUMIFS(Budget!$D:$D,Budget!$A:$A,A3,Budget!$B:$B,B3) -> 537660 | E3: =C3-D3 -> -34142 | F3: =SUMIFS(Actuals!$D:$D,Actuals!$A:$A,A3,Actuals!$B:$B,B3)+SUMIFS(Actuals!$E:$E,Actuals!$A:$A,A3,Actuals!$B:$B,B3)+SUMIFS(Actuals!$F:$F,Actuals!$A:$A,A3,Actuals!$B:$B,B3) -> 137948 | G3: =SUMIFS(Budget!$D:$D,Budget!$A:$A,A3,Budget!$B:$B,B3)+SUMIFS(Budget!$E:$E,Budget!$A:$A,A3,Budget!$B:$B,B3)+SUMIFS(Budget!$F:$F,Budget!$A:$A,A3,Budget!$B:$B,B3) -> 154843 | H3: =F3-G3 -> -16895 | I3: =IFERROR(E3/D3,0) -> -0.063501097 | J3: =IF(ABS(I3)>=5%,"Review","Within threshold") -> Review
A4: Retail | B4: Mar | C4: =SUMIFS(Actuals!$D:$D,Actuals!$A:$A,A4,Actuals!$B:$B,B4) -> 589110 | D4: =SUMIFS(Budget!$D:$D,Budget!$A:$A,A4,Budget!$B:$B,B4) -> 560320 | E4: =C4-D4 -> 28790 | F4: =SUMIFS(Actuals!$D:$D,Actuals!$A:$A,A4,Actuals!$B:$B,B4)+SUMIFS(Actuals!$E:$E,Actuals!$A:$A,A4,Actuals!$B:$B,B4)+SUMIFS(Actuals!$F:$F,Actuals!$A:$A,A4,Actuals!$B:$B,B4) -> 164648 | G4: =SUMIFS(Budget!$D:$D,Budget!$A:$A,A4,Budget!$B:$B,B4)+SUMIFS(Budget!$E:$E,Budget!$A:$A,A4,Budget!$B:$B,B4)+SUMIFS(Budget!$F:$F,Budget!$A:$A,A4,Budget!$B:$B,B4) -> 160986 | H4: =F4-G4 -> 3662 | I4: =IFERROR(E4/D4,0) -> 0.051381354 | J4: =IF(ABS(I4)>=5%,"Review","Within threshold") -> Review
A5: Retail | B5: Apr | C5: =SUMIFS(Actuals!$D:$D,Actuals!$A:$A,A5,Actuals!$B:$B,B5) -> 537914 | D5: =SUMIFS(Budget!$D:$D,Budget!$A:$A,A5,Budget!$B:$B,B5) -> 582980 | E5: =C5-D5 -> -45066 | F5: =SUMIFS(Actuals!$D:$D,Actuals!$A:$A,A5,Actuals!$B:$B,B5)+SUMIFS(Actuals!$E:$E,Actuals!$A:$A,A5,Actuals!$B:$B,B5)+SUMIFS(Actuals!$F:$F,Actuals!$A:$A,A5,Actuals!$B:$B,B5) -> 129573 | G5: =SUMIFS(Budget!$D:$D,Budget!$A:$A,A5,Budget!$B:$B,B5)+SUMIFS(Budget!$E:$E,Budget!$A:$A,A5,Budget!$B:$B,B5)+SUMIFS(Budget!$F:$F,Budget!$A:$A,A5,Budget!$B:$B,B5) -> 167128 | H5: =F5-G5 -> -37555 | I5: =IFERROR(E5/D5,0) -> -0.077302823 | J5: =IF(ABS(I5)>=5%,"Review","Within threshold") -> Review
A6: Retail | B6: May | C6: =SUMIFS(Actuals!$D:$D,Actuals!$A:$A,A6,Actuals!$B:$B,B6) -> 542347 | D6: =SUMIFS(Budget!$D:$D,Budget!$A:$A,A6,Budget!$B:$B,B6) -> 605640 | E6: =C6-D6 -> -63293 | F6: =SUMIFS(Actuals!$D:$D,Actuals!$A:$A,A6,Actuals!$B:$B,B6)+SUMIFS(Actuals!$E:$E,Actuals!$A:$A,A6,Actuals!$B:$B,B6)+SUMIFS(Actuals!$F:$F,Actuals!$A:$A,A6,Actuals!$B:$B,B6) -> 143588 | G6: =SUMIFS(Budget!$D:$D,Budget!$A:$A,A6,Budget!$B:$B,B6)+SUMIFS(Budget!$E:$E,Budget!$A:$A,A6,Budget!$B:$B,B6)+SUMIFS(Budget!$F:$F,Budget!$A:$A,A6,Budget!$B:$B,B6) -> 173271 | H6: =F6-G6 -> -29683 | I6: =IFERROR(E6/D6,0) -> -0.10450598 | J6: =IF(ABS(I6)>=5%,"Review","Within threshold") -> Review
A7: Retail | B7: Jun | C7: =SUMIFS(Actuals!$D:$D,Actuals!$A:$A,A7,Actuals!$B:$B,B7) -> 608028 | D7: =SUMIFS(Budget!$D:$D,Budget!$A:$A,A7,Budget!$B:$B,B7) -> 628300 | E7: =C7-D7 -> -20272 | F7: =SUMIFS(Actuals!$D:$D,Actuals!$A:$A,A7,Actuals!$B:$B,B7)+SUMIFS(Actuals!$E:$E,Actuals!$A:$A,A7,Actuals!$B:$B,B7)+SUMIFS(Actuals!$F:$F,Actuals!$A:$A,A7,Actuals!$B:$B,B7) -> 165403 | G7: =SUMIFS(Budget!$D:$D,Budget!$A:$A,A7,Budget!$B:$B,B7)+SUMIFS(Budget!$E:$E,Budget!$A:$A,A7,Budget!$B:$B,B7)+SUMIFS(Budget!$F:$F,Budget!$A:$A,A7,Budget!$B:$B,B7) -> 179414 | H7: =F7-G7 -> -14011 | I7: =IFERROR(E7/D7,0) -> -0.032264842 | J7: =IF(ABS(I7)>=5%,"Review","Within threshold") -> Within threshold
A8: Retail | B8: Jul | C8: =SUMIFS(Actuals!$D:$D,Actuals!$A:$A,A8,Actuals!$B:$B,B8) -> 644804 | D8: =SUMIFS(Budget!$D:$D,Budget!$A:$A,A8,Budget!$B:$B,B8) -> 650960 | E8: =C8-D8 -> -6156 | F8: =SUMIFS(Actuals!$D:$D,Actuals!$A:$A,A8,Actuals!$B:$B,B8)+SUMIFS(Actuals!$E:$E,Actuals!$A:$A,A8,Actuals!$B:$B,B8)+SUMIFS(Actuals!$F:$F,Actuals!$A:$A,A8,Actuals!$B:$B,B8) -> 196992 | G8: =SUMIFS(Budget!$D:$D,Budget!$A:$A,A8,Budget!$B:$B,B8)+SUMIFS(Budget!$E:$E,Budget!$A:$A,A8,Budget!$B:$B,B8)+SUMIFS(Budget!$F:$F,Budget!$A:$A,A8,Budget!$B:$B,B8) -> 185557 | H8: =F8-G8 -> 11435 | I8: =IFERROR(E8/D8,0) -> -0.0094568023 | J8: =IF(ABS(I8)>=5%,"Review","Within threshold") -> Within threshold
A9: Retail | B9: Aug | C9: =SUMIFS(Actuals!$D:$D,Actuals!$A:$A,A9,Actuals!$B:$B,B9) -> 615036 | D9: =SUMIFS(Budget!$D:$D,Budget!$A:$A,A9,Budget!$B:$B,B9) -> 673620 | E9: =C9-D9 -> -58584 | F9: =SUMIFS(Actuals!$D:$D,Actuals!$A:$A,A9,Actuals!$B:$B,B9)+SUMIFS(Actuals!$E:$E,Actuals!$A:$A,A9,Actuals!$B:$B,B9)+SUMIFS(Actuals!$F:$F,Actuals!$A:$A,A9,Actuals!$B:$B,B9) -> 142699 | G9: =SUMIFS(Budget!$D:$D,Budget!$A:$A,A9,Budget!$B:$B,B9)+SUMIFS(Budget!$E:$E,Budget!$A:$A,A9,Budget!$B:$B,B9)+SUMIFS(Budget!$F:$F,Budget!$A:$A,A9,Budget!$B:$B,B9) -> 191700 | H9: =F9-G9 -> -49001 | I9: =IFERROR(E9/D9,0) -> -0.086968914 | J9: =IF(ABS(I9)>=5%,"Review","Within threshold") -> Review
A10: Retail | B10: Sep | C10: =SUMIFS(Actuals!$D:$D,Actuals!$A:$A,A10,Actuals!$B:$B,B10) -> 648361 | D10: =SUMIFS(Budget!$D:$D,Budget!$A:$A,A10,Budget!$B:$B,B10) -> 696280 | E10: =C10-D10 -> -47919 | F10: =SUMIFS(Actuals!$D:$D,Actuals!$A:$A,A10,Actuals!$B:$B,B10)+SUMIFS(Actuals!$E:$E,Actuals!$A:$A,A10,Actuals!$B:$B,B10)+SUMIFS(Actuals!$F:$F,Actuals!$A:$A,A10,Actuals!$B:$B,B10) -> 166621 | G10: =SUMIFS(Budget!$D:$D,Budget!$A:$A,A10,Budget!$B:$B,B10)+SUMIFS(Budget!$E:$E,Budget!$A:$A,A10,Budget!$B:$B,B10)+SUMIFS(Budget!$F:$F,Budget!$A:$A,A10,Budget!$B:$B,B10) -> 197842 | H10: =F10-G10 -> -31221 | I10: =IFERROR(E10/D10,0) -> -0.068821451 | J10: =IF(ABS(I10)>=5%,"Review","Within threshold") -> Review
A11: Retail | B11: Oct | C11: =SUMIFS(Actuals!$D:$D,Actuals!$A:$A,A11,Actuals!$B:$B,B11) -> 750496 | D11: =SUMIFS(Budget!$D:$D,Budget!$A:$A,A11,Budget!$B:$B,B11) -> 718940 | E11: =C11-D11 -> 31556 | F11: =SUMIFS(Actuals!$D:$D,Actuals!$A:$A,A11,Actuals!$B:$B,B11)+SUMIFS(Actuals!$E:$E,Actuals!$A:$A,A11,Actuals!$B:$B,B11)+SUMIFS(Actuals!$F:$F,Actuals!$A:$A,A11,Actuals!$B:$B,B11) -> 230727 | G11: =SUMIFS(Budget!$D:$D,Budget!$A:$A,A11,Budget!$B:$B,B11)+SUMIFS(Budget!$E:$E,Budget!$A:$A,A11,Budget!$B:$B,B11)+SUMIFS(Budget!$F:$F,Budget!$A:$A,A11,Budget!$B:$B,B11) -> 203985 | H11: =F11-G11 -> 26742 | I11: =IFERROR(E11/D11,0) -> 0.043892397 | J11: =IF(ABS(I11)>=5%,"Review","Within threshold") -> Within threshold
A12: Retail | B12: Nov | C12: =SUMIFS(Actuals!$D:$D,Actuals!$A:$A,A12,Actuals!$B:$B,B12) -> 765301 | D12: =SUMIFS(Budget!$D:$D,Budget!$A:$A,A12,Budget!$B:$B,B12) -> 741600 | E12: =C12-D12 -> 23701 | F12: =SUMIFS(Actuals!$D:$D,Actuals!$A:$A,A12,Actuals!$B:$B,B12)+SUMIFS(Actuals!$E:$E,Actuals!$A:$A,A12,Actuals!$B:$B,B12)+SUMIFS(Actuals!$F:$F,Actuals!$A:$A,A12,Actuals!$B:$B,B12) -> 233168 | G12: =SUMIFS(Budget!$D:$D,Budget!$A:$A,A12,Budget!$B:$B,B12)+SUMIFS(Budget!$E:$E,Budget!$A:$A,A12,Budget!$B:$B,B12)+SUMIFS(Budget!$F:$F,Budget!$A:$A,A12,Budget!$B:$B,B12) -> 210128 | H12: =F12-G12 -> 23040 | I12: =IFERROR(E12/D12,0) -> 0.031959277 | J12: =IF(ABS(I12)>=5%,"Review","Within threshold") -> Within threshold
A13: Retail | B13: Dec | C13: =SUMIFS(Actuals!$D:$D,Actuals!$A:$A,A13,Actuals!$B:$B,B13) -> 733603 | D13: =SUMIFS(Budget!$D:$D,Budget!$A:$A,A13,Budget!$B:$B,B13) -> 764260 | E13: =C13-D13 -> -30657 | F13: =SUMIFS(Actuals!$D:$D,Actuals!$A:$A,A13,Actuals!$B:$B,B13)+SUMIFS(Actuals!$E:$E,Actuals!$A:$A,A13,Actuals!$B:$B,B13)+SUMIFS(Actuals!$F:$F,Actuals!$A:$A,A13,Actuals!$B:$B,B13) -> 205738 | G13: =SUMIFS(Budget!$D:$D,Budget!$A:$A,A13,Budget!$B:$B,B13)+SUMIFS(Budget!$E:$E,Budget!$A:$A,A13,Budget!$B:$B,B13)+SUMIFS(Budget!$F:$F,Budget!$A:$A,A13,Budget!$B:$B,B13) -> 216271 | H13: =F13-G13 -> -10533 | I13: =IFERROR(E13/D13,0) -> -0.040113312 | J13: =IF(ABS(I13)>=5%,"Review","Within threshold") -> Within threshold
... A49: Digital | B49: Dec | C49: =SUMIFS(Actuals!$D:$D,Actuals!$A:$A,A49,Actuals!$B:$B,B49) -> 923465 | D49: =SUMIFS(Budget!$D:$D,Budget!$A:$A,A49,Budget!$B:$B,B49) -> 1011460 | E49: =C49-D49 -> -87995 | F49: =SUMIFS(Actuals!$D:$D,Actuals!$A:$A,A49,Actuals!$B:$B,B49)+SUMIFS(Actuals!$E:$E,Actuals!$A:$A,A49,Actuals!$B:$B,B49)+SUMIFS(Actuals!$F:$F,Actuals!$A:$A,A49,Actuals!$B:$B,B49) -> 244357 | G49: =SUMIFS(Budget!$D:$D,Budget!$A:$A,A49,Budget!$B:$B,B49)+SUMIFS(Budget!$E:$E,Budget!$A:$A,A49,Budget!$B:$B,B49)+SUMIFS(Budget!$F:$F,Budget!$A:$A,A49,Budget!$B:$B,B49) -> 305647 | H49: =F49-G49 -> -61290 | I49: =IFERROR(E49/D49,0) -> -0.086998003 | J49: =IF(ABS(I49)>=5%,"Review","Within threshold") -> Review

Sheet Forecast
A1: Month | B1: Month No | C1: Base Revenue | D1: Downside Revenue | E1: Base EBITDA | F1: Downside EBITDA
A2: Jan | B2: 1 | C2: =SUMIFS(Actuals!$D:$D,Actuals!$C:$C,B2)*(1+Assumptions!$B$4) -> 2748990.2 | D2: =SUMIFS(Actuals!$D:$D,Actuals!$C:$C,B2)*(1+Assumptions!$B$5) -> 2515585.4 | E2: =C2*(1-Assumptions!$B$6)-ABS(SUMIFS(Actuals!$F:$F,Actuals!$C:$C,B2))*(1+Assumptions!$B$8) -> 873307.03 | F2: =D2*(1-Assumptions!$B$7)-ABS(SUMIFS(Actuals!$F:$F,Actuals!$C:$C,B2))*(1+Assumptions!$B$9) -> 606182.56
A3: Feb | B3: 2 | C3: =SUMIFS(Actuals!$D:$D,Actuals!$C:$C,B3)*(1+Assumptions!$B$4) -> 2652524.9 | D3: =SUMIFS(Actuals!$D:$D,Actuals!$C:$C,B3)*(1+Assumptions!$B$5) -> 2427310.5 | E3: =C3*(1-Assumptions!$B$6)-ABS(SUMIFS(Actuals!$F:$F,Actuals!$C:$C,B3))*(1+Assumptions!$B$8) -> 796940.34 | F3: =D3*(1-Assumptions!$B$7)-ABS(SUMIFS(Actuals!$F:$F,Actuals!$C:$C,B3))*(1+Assumptions!$B$9) -> 537431.08
A4: Mar | B4: 3 | C4: =SUMIFS(Actuals!$D:$D,Actuals!$C:$C,B4)*(1+Assumptions!$B$4) -> 2791617.1 | D4: =SUMIFS(Actuals!$D:$D,Actuals!$C:$C,B4)*(1+Assumptions!$B$5) -> 2554593 | E4: =C4*(1-Assumptions!$B$6)-ABS(SUMIFS(Actuals!$F:$F,Actuals!$C:$C,B4))*(1+Assumptions!$B$8) -> 853113.91 | F4: =D4*(1-Assumptions!$B$7)-ABS(SUMIFS(Actuals!$F:$F,Actuals!$C:$C,B4))*(1+Assumptions!$B$9) -> 580549.81
A5: Apr | B5: 4 | C5: =SUMIFS(Actuals!$D:$D,Actuals!$C:$C,B5)*(1+Assumptions!$B$4) -> 3009439.6 | D5: =SUMIFS(Actuals!$D:$D,Actuals!$C:$C,B5)*(1+Assumptions!$B$5) -> 2753921.2 | E5: =C5*(1-Assumptions!$B$6)-ABS(SUMIFS(Actuals!$F:$F,Actuals!$C:$C,B5))*(1+Assumptions!$B$8) -> 949548.35 | F5: =D5*(1-Assumptions!$B$7)-ABS(SUMIFS(Actuals!$F:$F,Actuals!$C:$C,B5))*(1+Assumptions!$B$9) -> 656865.57
A6: May | B6: 5 | C6: =SUMIFS(Actuals!$D:$D,Actuals!$C:$C,B6)*(1+Assumptions!$B$4) -> 2874599.2 | D6: =SUMIFS(Actuals!$D:$D,Actuals!$C:$C,B6)*(1+Assumptions!$B$5) -> 2630529.4 | E6: =C6*(1-Assumptions!$B$6)-ABS(SUMIFS(Actuals!$F:$F,Actuals!$C:$C,B6))*(1+Assumptions!$B$8) -> 833355.34 | F6: =D6*(1-Assumptions!$B$7)-ABS(SUMIFS(Actuals!$F:$F,Actuals!$C:$C,B6))*(1+Assumptions!$B$9) -> 550953.86
A7: Jun | B7: 6 | C7: =SUMIFS(Actuals!$D:$D,Actuals!$C:$C,B7)*(1+Assumptions!$B$4) -> 3072839.3 | D7: =SUMIFS(Actuals!$D:$D,Actuals!$C:$C,B7)*(1+Assumptions!$B$5) -> 2811937.9 | E7: =C7*(1-Assumptions!$B$6)-ABS(SUMIFS(Actuals!$F:$F,Actuals!$C:$C,B7))*(1+Assumptions!$B$8) -> 920291.19 | F7: =D7*(1-Assumptions!$B$7)-ABS(SUMIFS(Actuals!$F:$F,Actuals!$C:$C,B7))*(1+Assumptions!$B$9) -> 619547.82
A8: Jul | B8: 7 | C8: =SUMIFS(Actuals!$D:$D,Actuals!$C:$C,B8)*(1+Assumptions!$B$4) -> 3274845.6 | D8: =SUMIFS(Actuals!$D:$D,Actuals!$C:$C,B8)*(1+Assumptions!$B$5) -> 2996792.7 | E8: =C8*(1-Assumptions!$B$6)-ABS(SUMIFS(Actuals!$F:$F,Actuals!$C:$C,B8))*(1+Assumptions!$B$8) -> 1037715.2 | F8: =D8*(1-Assumptions!$B$7)-ABS(SUMIFS(Actuals!$F:$F,Actuals!$C:$C,B8))*(1+Assumptions!$B$9) -> 719390.62
A9: Aug | B9: 8 | C9: =SUMIFS(Actuals!$D:$D,Actuals!$C:$C,B9)*(1+Assumptions!$B$4) -> 3148031.5 | D9: =SUMIFS(Actuals!$D:$D,Actuals!$C:$C,B9)*(1+Assumptions!$B$5) -> 2880745.8 | E9: =C9*(1-Assumptions!$B$6)-ABS(SUMIFS(Actuals!$F:$F,Actuals!$C:$C,B9))*(1+Assumptions!$B$8) -> 909525.2 | F9: =D9*(1-Assumptions!$B$7)-ABS(SUMIFS(Actuals!$F:$F,Actuals!$C:$C,B9))*(1+Assumptions!$B$9) -> 600142.45
A10: Sep | B10: 9 | C10: =SUMIFS(Actuals!$D:$D,Actuals!$C:$C,B10)*(1+Assumptions!$B$4) -> 3357482.2 | D10: =SUMIFS(Actuals!$D:$D,Actuals!$C:$C,B10)*(1+Assumptions!$B$5) -> 3072412.9 | E10: =C10*(1-Assumptions!$B$6)-ABS(SUMIFS(Actuals!$F:$F,Actuals!$C:$C,B10))*(1+Assumptions!$B$8) -> 1009105.2 | F10: =D10*(1-Assumptions!$B$7)-ABS(SUMIFS(Actuals!$F:$F,Actuals!$C:$C,B10))*(1+Assumptions!$B$9) -> 680640.55
A11: Oct | B11: 10 | C11: =SUMIFS(Actuals!$D:$D,Actuals!$C:$C,B11)*(1+Assumptions!$B$4) -> 3600124.6 | D11: =SUMIFS(Actuals!$D:$D,Actuals!$C:$C,B11)*(1+Assumptions!$B$5) -> 3294453.7 | E11: =C11*(1-Assumptions!$B$6)-ABS(SUMIFS(Actuals!$F:$F,Actuals!$C:$C,B11))*(1+Assumptions!$B$8) -> 1114282.4 | F11: =D11*(1-Assumptions!$B$7)-ABS(SUMIFS(Actuals!$F:$F,Actuals!$C:$C,B11))*(1+Assumptions!$B$9) -> 763320.28
A12: Nov | B12: 11 | C12: =SUMIFS(Actuals!$D:$D,Actuals!$C:$C,B12)*(1+Assumptions!$B$4) -> 3618575 | D12: =SUMIFS(Actuals!$D:$D,Actuals!$C:$C,B12)*(1+Assumptions!$B$5) -> 3311337.5 | E12: =C12*(1-Assumptions!$B$6)-ABS(SUMIFS(Actuals!$F:$F,Actuals!$C:$C,B12))*(1+Assumptions!$B$8) -> 1104082.1 | F12: =D12*(1-Assumptions!$B$7)-ABS(SUMIFS(Actuals!$F:$F,Actuals!$C:$C,B12))*(1+Assumptions!$B$9) -> 750709.39
A13: Dec | B13: 12 | C13: =SUMIFS(Actuals!$D:$D,Actuals!$C:$C,B13)*(1+Assumptions!$B$4) -> 3635121.6 | D13: =SUMIFS(Actuals!$D:$D,Actuals!$C:$C,B13)*(1+Assumptions!$B$5) -> 3326479.2 | E13: =C13*(1-Assumptions!$B$6)-ABS(SUMIFS(Actuals!$F:$F,Actuals!$C:$C,B13))*(1+Assumptions!$B$8) -> 1077008.9 | F13: =D13*(1-Assumptions!$B$7)-ABS(SUMIFS(Actuals!$F:$F,Actuals!$C:$C,B13))*(1+Assumptions!$B$9) -> 720784.8

Sheet Dashboard
B2: NORTHSTAR FP&A DASHBOARD
B4: Actual Revenue | E4: Budget Revenue | H4: Revenue Variance | K4: Actual EBITDA
B5: 35645463 | E5: 36635040 | H5: -989577 | K5: 10366229

Sheet Controls
A1: Workbook control checks
A3: Check | B3: Calculated | C3: Expected
A4: Actual revenue control | B4: =SUM(Actuals!D:D) -> 35645463 | C4: 35645463
A5: Budget revenue control | B5: =SUM(Budget!D:D) -> 36635040 | C5: 36635040
A6: Variance identity | B6: =SUM(Analysis!E:E)-(SUM(Analysis!C:C)-SUM(Analysis!D:D)) -> 0 | C6: 0
A7: Formula status count | B7: =COUNTIF(Analysis!J:J,"Review") -> 25 | C7: 25
