Workbook

Sheet Start Here
A1: Lab 5: Analyse Variances and Build a Dashboard with Copilot
A3: Course | B3: Generative AI for Finance and Fintech (TGS-2026065050)
A4: TSC mapping | B4: K1 · A2
A5: Objective | B5: Use Copilot in Excel to analyse budget variances and build an auditable management dashboard.
A6: Scenario | B6: Northstar's CFO needs a monthly performance dashboard and commentary that survives scrutiny in the board meeting.
A7: Expected output | B7: An editable dashboard with actual, budget, variance and forecast views plus verified commentary.
A8: Data notice | B8: All names, accounts, transactions and scores are synthetic. Do not replace them with live personal or customer data.
A9: Acceptance | B9: All formula checks pass; total variance equals actual less budget; charts stay linked to source data; commentary separates evidenced fact from labelled hypothesis.

Sheet PL Data
A1: Period | B1: Department | C1: AccountCode | D1: AccountName | E1: AccountType | F1: ActualSGD | G1: BudgetSGD | H1: VarianceSGD
A2: 2026-01 | B2: Digital Payments | C2: 4000 | D2: Interest Income | E2: Revenue | F2: 346016.39 | G2: 311617.19 | H2: 34399.2
A3: 2026-01 | B3: Digital Payments | C3: 4100 | D3: Fee and Commission Income | E3: Revenue | F3: 176057.06 | G3: 168293.1 | H3: 7763.96
A4: 2026-01 | B4: Digital Payments | C4: 4200 | D4: Transaction Revenue | E4: Revenue | F4: 107950.83 | G4: 106368.11 | H4: 1582.72
A5: 2026-01 | B5: Digital Payments | C5: 5000 | D5: Cost of Service Delivery | E5: COGS | F5: -168074.28 | G5: -159160.94 | H5: -8913.34
A6: 2026-01 | B6: Digital Payments | C6: 6100 | D6: Marketing and Acquisition | E6: Opex | F6: -60153.21 | G6: -67090.59 | H6: 6937.38
A7: 2026-01 | B7: Digital Payments | C7: 6200 | D7: Technology and Cloud | E7: Opex | F7: -68606.83 | G7: -66831.34 | H7: -1775.49
A8: 2026-01 | B8: Digital Payments | C8: 6300 | D8: People Cost | E8: Opex | F8: -152662.27 | G8: -166902.45 | H8: 14240.18
A9: 2026-01 | B9: Digital Payments | C9: 6400 | D9: Premises and Admin | E9: Opex | F9: -30516.88 | G9: -27571.89 | H9: -2944.99
A10: 2026-01 | B10: Digital Payments | C10: 6500 | D10: Compliance and Risk | E10: Opex | F10: -25455.29 | G10: -27967.31 | H10: 2512.02
A11: 2026-01 | B11: Digital Payments | C11: 7000 | D11: Credit Loss Provision | E11: Provision | F11: -19503.27 | G11: -20452.38 | H11: 949.11
A12: 2026-01 | B12: Enterprise | C12: 4000 | D12: Interest Income | E12: Revenue | F12: 906737.36 | G12: 909603.18 | H12: -2865.82
A13: 2026-01 | B13: Enterprise | C13: 4100 | D13: Fee and Commission Income | E13: Revenue | F13: 469083.76 | G13: 464201.85 | H13: 4881.91
... A241: 2026-06 | B241: SME Lending | C241: 7000 | D241: Credit Loss Provision | E241: Provision | F241: -33608.74 | G241: -32364.93 | H241: -1243.81

Sheet Analysis
A1: Department summary — build these with Copilot, then audit every formula
A3: Department | B3: Actual | C3: Budget | D3: Variance | E3: Variance % | F3: Material?
A4: Digital Payments | B4: =SUMIFS('PL Data'!$F$2:$F$241,'PL Data'!$B$2:$B$241,$A4) -> 634054.51 | C4: =SUMIFS('PL Data'!$G$2:$G$241,'PL Data'!$B$2:$B$241,$A4) -> 615023.35 | D4: =B4-C4 -> 19031.16 | E4: =IFERROR(D4/ABS(C4),0) -> 0.030943801 | F4: =IF(OR(ABS(D4)>50000,ABS(E4)>0.1),"MATERIAL","")
A5: Enterprise | B5: =SUMIFS('PL Data'!$F$2:$F$241,'PL Data'!$B$2:$B$241,$A5) -> 1674178.1 | C5: =SUMIFS('PL Data'!$G$2:$G$241,'PL Data'!$B$2:$B$241,$A5) -> 1709724 | D5: =B5-C5 -> -35545.89 | E5: =IFERROR(D5/ABS(C5),0) -> -0.020790426 | F5: =IF(OR(ABS(D5)>50000,ABS(E5)>0.1),"MATERIAL","")
A6: Retail Banking | B6: =SUMIFS('PL Data'!$F$2:$F$241,'PL Data'!$B$2:$B$241,$A6) -> 1421659.4 | C6: =SUMIFS('PL Data'!$G$2:$G$241,'PL Data'!$B$2:$B$241,$A6) -> 1543569.9 | D6: =B6-C6 -> -121910.43 | E6: =IFERROR(D6/ABS(C6),0) -> -0.078979536 | F6: =IF(OR(ABS(D6)>50000,ABS(E6)>0.1),"MATERIAL","") -> MATERIAL
A7: SME Lending | B7: =SUMIFS('PL Data'!$F$2:$F$241,'PL Data'!$B$2:$B$241,$A7) -> 1037367.4 | C7: =SUMIFS('PL Data'!$G$2:$G$241,'PL Data'!$B$2:$B$241,$A7) -> 1179772.3 | D7: =B7-C7 -> -142404.94 | E7: =IFERROR(D7/ABS(C7),0) -> -0.12070544 | F7: =IF(OR(ABS(D7)>50000,ABS(E7)>0.1),"MATERIAL","") -> MATERIAL
A10: Monthly trend
A12: Period | B12: Actual | C12: Budget | D12: Variance | E12: Variance %
A13: 2026-01 | B13: =SUMIFS('PL Data'!$F$2:$F$241,'PL Data'!$A$2:$A$241,$A13) -> 771247.89 | C13: =SUMIFS('PL Data'!$G$2:$G$241,'PL Data'!$A$2:$A$241,$A13) -> 720466.56 | D13: =B13-C13 -> 50781.33 | E13: =IFERROR(D13/ABS(C13),0) -> 0.070483951
A14: 2026-02 | B14: =SUMIFS('PL Data'!$F$2:$F$241,'PL Data'!$A$2:$A$241,$A14) -> 798523.22 | C14: =SUMIFS('PL Data'!$G$2:$G$241,'PL Data'!$A$2:$A$241,$A14) -> 928660.37 | D14: =B14-C14 -> -130137.15 | E14: =IFERROR(D14/ABS(C14),0) -> -0.14013428
A15: 2026-03 | B15: =SUMIFS('PL Data'!$F$2:$F$241,'PL Data'!$A$2:$A$241,$A15) -> 689206.92 | C15: =SUMIFS('PL Data'!$G$2:$G$241,'PL Data'!$A$2:$A$241,$A15) -> 849744.66 | D15: =B15-C15 -> -160537.74 | E15: =IFERROR(D15/ABS(C15),0) -> -0.18892468
A16: 2026-04 | B16: =SUMIFS('PL Data'!$F$2:$F$241,'PL Data'!$A$2:$A$241,$A16) -> 866470.14 | C16: =SUMIFS('PL Data'!$G$2:$G$241,'PL Data'!$A$2:$A$241,$A16) -> 854616.19 | D16: =B16-C16 -> 11853.95 | E16: =IFERROR(D16/ABS(C16),0) -> 0.013870495
A17: 2026-05 | B17: =SUMIFS('PL Data'!$F$2:$F$241,'PL Data'!$A$2:$A$241,$A17) -> 812492.36 | C17: =SUMIFS('PL Data'!$G$2:$G$241,'PL Data'!$A$2:$A$241,$A17) -> 845037.68 | D17: =B17-C17 -> -32545.32 | E17: =IFERROR(D17/ABS(C17),0) -> -0.038513454
A18: 2026-06 | B18: =SUMIFS('PL Data'!$F$2:$F$241,'PL Data'!$A$2:$A$241,$A18) -> 829318.85 | C18: =SUMIFS('PL Data'!$G$2:$G$241,'PL Data'!$A$2:$A$241,$A18) -> 849564.02 | D18: =B18-C18 -> -20245.17 | E18: =IFERROR(D18/ABS(C18),0) -> -0.02383007

Sheet Dashboard
A1: KPI tiles — every tile must be a formula, never a typed value
A3: KPI | B3: Value | C3: Control total | D3: Reconciles?
A4: Net profit H1 FY2026 | B4: =SUM('PL Data'!F2:F241) -> 4767259.4 | C4: 4767259.4 | D4: =IF(ROUND(B4,2)=ROUND(C4,2),"OK","CHECK") -> OK
A5: Budgeted net profit | B5: =SUM('PL Data'!G2:G241) -> 5048089.5 | C5: 5048089.5 | D5: =IF(ROUND(B5,2)=ROUND(C5,2),"OK","CHECK") -> OK
A6: Variance to budget | B6: =B4-B5 -> -280830.1 | C6: -280830.1 | D6: =IF(ROUND(B6,2)=ROUND(C6,2),"OK","CHECK") -> OK

Sheet Commentary
A1: Commentary — separate what the data shows from what you are inferring
A2: Materiality: greater than SGD 50,000 or 10% of budget, whichever is lower (POL-FIN-002).
A5: Department / account | B5: Variance SGD | C5: Statement | D5: Fact or hypothesis? | E5: Owner to confirm
